qwak/Errors.py
qwak/GraphicalQWAK.py
qwak/Operator.py
qwak/ProbabilityDistribution.py
qwak/QuantumWalk.py
qwak/State.py
qwak/StochasticOperator.py
qwak/StochasticProbabilityDistribution.py
qwak/StochasticQuantumWalk.py
qwak/StochasticQwak.py
qwak/__init__.py
qwak/qwak.py
utils/PerfectStateTransfer.py
utils/__init__.py
utils/jsonTools.py
utils/plotTools.py
qwak_sim-2023.1014a0.dist-info/LICENSE
qwak_sim-2023.1014a0.dist-info/METADATA
qwak_sim-2023.1014a0.dist-info/WHEEL
qwak_sim-2023.1014a0.dist-info/top_level.txt
qwak_sim-2023.1014a0.dist-info/RECORD
