Metadata-Version: 2.1
Name: qwak-sim
Version: 2023.1014a0
Summary: Simulate Continuous-Time Quantum Walks
Home-page: https://github.com/qwchagas/qwak
Author: Jaime Santos
Author-email: Jaime Santos <jaimepereirasantos123@gmail.com>, Bruno Chagas <na@na.na>, Rodrigo Chaves <na@na.na>, Lorenzo Buffoni <na@na.na>
License: GNU GENERAL PUBLIC LICENSE
Project-URL: Homepage, https://github.com/JaimePSantos/QWAK
Project-URL: documentation, https://jaimepsantos.github.io/QWAK/
Keywords: quantum,ctqw,simulator
Classifier: License :: OSI Approved :: GNU General Public License (GPL)
Requires-Python: >=3.8
License-File: LICENSE
Requires-Dist: numpy
Requires-Dist: scipy
Requires-Dist: sympy
Requires-Dist: matplotlib
Requires-Dist: networkx
Requires-Dist: qutip
Provides-Extra: dev
Requires-Dist: autopep8 ; extra == 'dev'
Requires-Dist: sphinx ; extra == 'dev'
Requires-Dist: pytest ; extra == 'dev'
